setuptools_cmmi/__init__.py
setuptools_cmmi/process_cmmi.py
setuptools_cmmi/tests/__init__.py
setuptools_cmmi/tests/cmmi_utils.py
setuptools_cmmi/tests/test_entry_point.py
setuptools_cmmi/tests/test_process_cmmi.py
setuptools_cmmi-0.1.1.dist-info/DESCRIPTION.rst
setuptools_cmmi-0.1.1.dist-info/METADATA
setuptools_cmmi-0.1.1.dist-info/RECORD
setuptools_cmmi-0.1.1.dist-info/WHEEL
setuptools_cmmi-0.1.1.dist-info/entry_points.txt
setuptools_cmmi-0.1.1.dist-info/metadata.json
setuptools_cmmi-0.1.1.dist-info/top_level.txt
