Metadata-Version: 2.0
Name: setuptools-cmmi
Version: 0.1.1
Summary: Egg to handle the CMMI custom task in setuptools.
Home-page: https://github.com/zillow/setuptools-cmmi
Author: padev
Author-email: padev@zillowgroup.com
License: UNKNOWN
Platform: UNKNOWN
Classifier: Development Status :: 3 - Alpha
Classifier: Intended Audience :: Developers
Classifier: Topic :: Software Development :: Build Tools
Classifier: License :: OSI Approved :: Apache Software License
Classifier: Programming Language :: Python
Classifier: Programming Language :: Python :: 2
Classifier: Programming Language :: Python :: 2.7
Classifier: Programming Language :: Python :: 3
Classifier: Programming Language :: Python :: 3.5
Requires-Dist: mock
Requires-Dist: setuptools (>=0.5)
